cancelable/__init__.py
cancelable_py-0.0.2.dist-info/LICENSE
cancelable_py-0.0.2.dist-info/METADATA
cancelable_py-0.0.2.dist-info/WHEEL
cancelable_py-0.0.2.dist-info/top_level.txt
cancelable_py-0.0.2.dist-info/RECORD
