Metadata-Version: 2.1
Name: cancelable-py
Version: 0.0.2
Summary: A package that allows to cancel, certain functions that can be a pain, when working with threading.
Home-page: https://github.com/jona799t/Cancelable
Author: jona799t
License: UNKNOWN
Keywords: python,threading,sleep,cancelable
Platform: UNKNOWN
Classifier: Development Status :: 1 - Planning
Classifier: Intended Audience :: Developers
Classifier: Programming Language :: Python :: 3
Classifier: Operating System :: Unix
Classifier: Operating System :: MacOS :: MacOS X
Classifier: Operating System :: Microsoft :: Windows
